pytrf.cp312-win_amd64.pyd
pytrfcli.py
pytrf-1.4.2.dist-info/LICENSE
pytrf-1.4.2.dist-info/METADATA
pytrf-1.4.2.dist-info/WHEEL
pytrf-1.4.2.dist-info/entry_points.txt
pytrf-1.4.2.dist-info/top_level.txt
pytrf-1.4.2.dist-info/RECORD
